clone/__init__.py
clone/__main__.py
clone-0.0.dist-info/DESCRIPTION.rst
clone-0.0.dist-info/METADATA
clone-0.0.dist-info/RECORD
clone-0.0.dist-info/WHEEL
clone-0.0.dist-info/entry_points.txt
clone-0.0.dist-info/metadata.json
clone-0.0.dist-info/top_level.txt
