Metadata-Version: 1.0
Name: clone
Version: 0.0
Summary: Clone Git repositories without installing Git
Home-page: https://github.com/hosford42/clone
Author: Aaron Hosford
Author-email: hosford42@gmail.com
License: MIT
Platform: UNKNOWN
